CHANGES.rst
LICENSE.rst
MANIFEST.in
README.rst
setup.py
js/__init__.py
js.dynatree.egg-info/PKG-INFO
js.dynatree.egg-info/SOURCES.txt
js.dynatree.egg-info/dependency_links.txt
js.dynatree.egg-info/entry_points.txt
js.dynatree.egg-info/namespace_packages.txt
js.dynatree.egg-info/not-zip-safe
js.dynatree.egg-info/requires.txt
js.dynatree.egg-info/top_level.txt
js/dynatree/__init__.py
js/dynatree/test_jquery.dynatree.js.txt
js/dynatree/resources/.DS_Store
js/dynatree/resources/GPL-LICENSE.txt
js/dynatree/resources/MIT-License.txt
js/dynatree/resources/jquery.dynatree.js
js/dynatree/resources/jquery.dynatree.min.js
js/dynatree/resources/skin/icons-rtl.gif
js/dynatree/resources/skin/icons.gif
js/dynatree/resources/skin/loading.gif
js/dynatree/resources/skin/ui.dynatree.css
js/dynatree/resources/skin/ui.dynatree.min.css
js/dynatree/resources/skin/vline-rtl.gif
js/dynatree/resources/skin/vline.gif
js/dynatree/resources/skin-vista/icons.gif
js/dynatree/resources/skin-vista/loading.gif
js/dynatree/resources/skin-vista/ui.dynatree.css
js/dynatree/resources/skin-vista/ui.dynatree.min.css