Metadata-Version: 1.0
Name: js.dynatree
Version: 1.2.2
Summary: Fanstatic packaging of jquery.dynatree.js
Home-page: UNKNOWN
Author: Andreas Kaiser
Author-email: disko@binary-punks.com
License: BSD
Platform: UNKNOWN
